fastloop/__init__.py
fastloop/config.default.yaml
fastloop/config.py
fastloop/constants.py
fastloop/context.py
fastloop/exceptions.py
fastloop/executor.py
fastloop/fastloop.py
fastloop/logging.py
fastloop/loop.py
fastloop/models.py
fastloop/monitor.py
fastloop/scheduler.py
fastloop/task.py
fastloop/types.py
fastloop/utils.py
fastloop/workflow.py
fastloop/cli/__init__.py
fastloop/integrations/__init__.py
fastloop/integrations/slack.py
fastloop/integrations/surge.py
fastloop/integrations/telnyx.py
fastloop/state/__init__.py
fastloop/state/state.py
fastloop/state/state_redis.py
fastloop/state/state_s3.py
fastloop-0.1.117.dist-info/METADATA
fastloop-0.1.117.dist-info/WHEEL
fastloop-0.1.117.dist-info/RECORD
