Metadata-Version: 2.4
Name: fastloop
Version: 0.1.117
Summary: A Python package for deploying stateful loops
Project-URL: Homepage, https://github.com/beam-cloud/fastloop
Project-URL: Repository, https://github.com/beam-cloud/fastloop
Project-URL: Issues, https://github.com/beam-cloud/fastloop/issues
Author-email: Luke Lombardi <luke@beaml.cloud>
License: MIT
Keywords: agentic,ai,baml,workflow
Classifier: Development Status :: 3 - Alpha
Classifier: Intended Audience :: Developers
Classifier: License :: OSI Approved :: MIT License
Classifier: Programming Language :: Python :: 3
Classifier: Programming Language :: Python :: 3.12
Requires-Python: >=3.12
Requires-Dist: aioboto3>=15.0.0
Requires-Dist: aiohttp>=3.9.0
Requires-Dist: cloudpickle>=3.1.1
Requires-Dist: croniter>=2.0.0
Requires-Dist: fastapi>=0.115.14
Requires-Dist: fastmcp==2.9.0
Requires-Dist: httpx>=0.24.0
Requires-Dist: hypercorn>=0.17.3
Requires-Dist: pydantic>=2.0.0
Requires-Dist: pyyaml>=6.0
Requires-Dist: redis>=6.2.0
Requires-Dist: slack-sdk>=3.27.0
Provides-Extra: dev
Requires-Dist: build>=1.0.0; extra == 'dev'
Requires-Dist: pytest-asyncio>=0.23.0; extra == 'dev'
Requires-Dist: pytest>=7.0.0; extra == 'dev'
Requires-Dist: ruff>=0.8.0; extra == 'dev'
Requires-Dist: twine>=4.0.0; extra == 'dev'
